dna_electrons/__init__.py
dna_electrons/cli.py
dna_electrons/core.py
dna_electrons/io.py
dna_electrons-0.2.1.dist-info/licenses/LICENSE
dna_electrons-0.2.1.dist-info/METADATA
dna_electrons-0.2.1.dist-info/WHEEL
dna_electrons-0.2.1.dist-info/entry_points.txt
dna_electrons-0.2.1.dist-info/top_level.txt
dna_electrons-0.2.1.dist-info/RECORD
