Metadata-Version: 2.4
Name: dna-electrons
Version: 0.2.1
Summary: Compute total electrons for DNA sequences with FASTA parsing and Biopython integration.
Author: Yash Munnalal Gupta
License: MIT License
Project-URL: Homepage, https://github.com/yashmgupta/dna-electrons
Project-URL: Issues, https://github.com/yashmgupta/dna-electrons/issues
Project-URL: Repository, https://github.com/yashmgupta/dna-electrons
Classifier: License :: OSI Approved :: MIT License
Classifier: Programming Language :: Python :: 3
Classifier: Programming Language :: Python :: 3 :: Only
Classifier: Programming Language :: Python :: 3.8
Classifier: Programming Language :: Python :: 3.9
Classifier: Programming Language :: Python :: 3.10
Classifier: Programming Language :: Python :: 3.11
Classifier: Programming Language :: Python :: 3.12
Classifier: Topic :: Scientific/Engineering :: Bio-Informatics
Requires-Python: >=3.8
License-File: LICENSE
Requires-Dist: biopython>=1.80
Dynamic: license-file
